odoo/addons/mail_template_operating_unit/README.rst
odoo/addons/mail_template_operating_unit/__init__.py
odoo/addons/mail_template_operating_unit/__manifest__.py
odoo/addons/mail_template_operating_unit/i18n/it.po
odoo/addons/mail_template_operating_unit/i18n/mail_template_operating_unit.pot
odoo/addons/mail_template_operating_unit/models/__init__.py
odoo/addons/mail_template_operating_unit/models/mail.py
odoo/addons/mail_template_operating_unit/readme/CONTRIBUTORS.rst
odoo/addons/mail_template_operating_unit/readme/DESCRIPTION.rst
odoo/addons/mail_template_operating_unit/readme/USAGE.rst
odoo/addons/mail_template_operating_unit/security/mail_security.xml
odoo/addons/mail_template_operating_unit/static/description/icon.png
odoo/addons/mail_template_operating_unit/static/description/index.html
odoo/addons/mail_template_operating_unit/views/mail_template_view.xml
odoo14_addon_mail_template_operating_unit-14.0.1.0.1.dev7.dist-info/METADATA
odoo14_addon_mail_template_operating_unit-14.0.1.0.1.dev7.dist-info/WHEEL
odoo14_addon_mail_template_operating_unit-14.0.1.0.1.dev7.dist-info/top_level.txt
odoo14_addon_mail_template_operating_unit-14.0.1.0.1.dev7.dist-info/RECORD
